fild/__init__.py
fild/process/__init__.py
fild/process/common.py
fild/process/dictionary.py
fild/sdk/__init__.py
fild/sdk/array.py
fild/sdk/base_enum.py
fild/sdk/dates.py
fild/sdk/dictionary.py
fild/sdk/fakeable.py
fild/sdk/field.py
fild/sdk/types.py
fild-0.1.3.dist-info/licenses/LICENSE
fild-0.1.3.dist-info/METADATA
fild-0.1.3.dist-info/WHEEL
fild-0.1.3.dist-info/top_level.txt
fild-0.1.3.dist-info/RECORD
