Metadata-Version: 2.4
Name: fild
Version: 0.1.3
Summary: Library to describe contracts and generate data
Home-page: https://github.com/elenakulgavaya/fild
Author: Elena Kulgavaya
Author-email: elena.kulgavaya@gmail.com
Project-URL: Bug Tracker, https://github.com/elenakulgavaya/fild/issues
Classifier: Programming Language :: Python :: 3
Classifier: License :: OSI Approved :: MIT License
Classifier: Operating System :: OS Independent
Requires-Python: >=3.7
License-File: LICENSE
Requires-Dist: Faker==11.3.0
Requires-Dist: pytz==2021.3
Dynamic: license-file
